llama_index/py.typed
llama_index/vector_stores/wordlift/__init__.py
llama_index/vector_stores/wordlift/base.py
llama_index/vector_stores/wordlift/metadata_filters_to_filters.py
llama_index_vector_stores_wordlift-0.6.1.dist-info/METADATA
llama_index_vector_stores_wordlift-0.6.1.dist-info/WHEEL
llama_index_vector_stores_wordlift-0.6.1.dist-info/licenses/LICENSE
llama_index_vector_stores_wordlift-0.6.1.dist-info/RECORD
