Metadata-Version: 2.4
Name: llama-index-vector-stores-wordlift
Version: 0.6.1
Summary: llama-index vector_stores wordlift integration
Author-email: Your Name <you@example.com>
License-Expression: MIT
License-File: LICENSE
Requires-Python: <4.0,>=3.9
Requires-Dist: aiohttp-retry>=1.2
Requires-Dist: aiohttp>=3.7.4
Requires-Dist: docker<8,>=7.1.0
Requires-Dist: llama-index-core<0.15,>=0.13.0
Requires-Dist: pydantic<3.0,>=2.0
Requires-Dist: python-dateutil>=2.8.2
Requires-Dist: urllib3<3,>=1.21.1
Requires-Dist: wordlift-client<2,>=1.46.0
